README.rst
setup.py
espatools/__init__.py
espatools/__main__.py
espatools/meta.py
espatools/raster.py
espatools/read.py
espatools.egg-info/PKG-INFO
espatools.egg-info/SOURCES.txt
espatools.egg-info/dependency_links.txt
espatools.egg-info/requires.txt
espatools.egg-info/top_level.txt