Metadata-Version: 2.1
Name: espatools
Version: 0.0.5
Summary: Landsat raster file I/O
Home-page: https://github.com/OpenGeoVis/espatools
Author: Bane Sullivan
Author-email: info@pvgeo.org
License: UNKNOWN
Platform: UNKNOWN
Classifier: Programming Language :: Python
Classifier: License :: OSI Approved :: BSD License
Classifier: Operating System :: OS Independent
Classifier: Topic :: Scientific/Engineering
Classifier: Topic :: Scientific/Engineering :: Visualization
Classifier: Topic :: Scientific/Engineering :: GIS
Classifier: Intended Audience :: Science/Research
Classifier: Natural Language :: English
